README.rst
setup.py
asar/__init__.py
asar/archive.py
pyasar.egg-info/PKG-INFO
pyasar.egg-info/SOURCES.txt
pyasar.egg-info/dependency_links.txt
pyasar.egg-info/top_level.txt