Metadata-Version: 1.0
Name: pyasar
Version: 1.0.8
Summary: Library for working with Electron's ASAR archives.
Home-page: https://github.com/Photonios/pyasar.git
Author: Swen Kooij (Photonios)
Author-email: photonios@outlook.com
License: UNKNOWN
Keywords: asar,electron,pyasar
Platform: UNKNOWN
